[
  {
    "key" : "archer",
    "name" : "کماندار",
    "cost": 70,
    "combat type": "archery",
    "combat strength": 4,
    "ranged combat strength": 6,
    "range": 2,
    "movement": 2,
    "resources required": "None",
    "technology required": "archery",
    "type": "ANCIENT_ERA_UNITS"

  },
    {
      "key" : "chariot Archer",
      "name" : "ارابه کماندار",
      "cost": 60,
      "combat type": "mounted",
      "combat strength": 3,
      "ranged combat strength": 6,
      "range": 2,
      "movement": 4,
      "resources required": "horses",
      "technology required": "the wheel",
      "type": "ANCIENT_ERA_UNITS"
    },
    {
      "key" : "scout",
      "name" : "دیده بانی",
      "cost": 25,
      "combat type": "recon",
      "combat strength": 4,
      "ranged combat strength": "N/A",
      "range": "N/A",
      "movement": 2,
      "resources required": "None",
      "technology required": "None",
      "type": "ANCIENT_ERA_UNITS"
    },
  {
    "key" : "settler",
    "name" : "شهرک نشین",
    "cost": 89,
    "combat type": "civilian",
    "combat strength": "N/A",
    "ranged combat strength": "N/A",
    "range": "N/A",
    "movement": 2,
    "resources required": "None",
    "technology required": "None",
    "type": "ANCIENT_ERA_UNITS"
  },
  {
    "key" : "spearman",
    "name" : "نیزه دار",
    "cost": 50,
    "combat type": "melee",
    "combat strength": 7,
    "ranged combat strength": "N/A",
    "range": "N/A",
    "movement": 2,
    "resources required": "None",
    "technology required": "Bronze Working",
    "type": "ANCIENT_ERA_UNITS"
  },
  {
    "key" : "warrior",
    "name" : "جنگجو",
    "cost": 40,
    "combat type": "melee",
    "combat strength": 6,
    "ranged combat strength": "N/A",
    "range": "N/A",
    "movement": 2,
    "resources required": 2,
    "travelCosts": "None",
    "technology required":"None",
    "type": "ANCIENT_ERA_UNITS"
  },
  {
    "key" : "worker",
    "name" : "کارگر",
    "cost": 70,
    "combat type": "civilian",
    "combat strength": "N/A",
    "ranged combat strength": "N/A",
    "range": "N/A",
    "movement": 2,
    "resources required": 2,
    "travelCosts": "None",
    "technology required": "None",
    "type": "ANCIENT_ERA_UNITS"
  },
  {
    "key" : "catapult",
    "name" : "منجنیق",
    "cost": 100,
    "combat type": "siege",
    "combat strength": 4,
    "ranged combat strength": 14,
    "range": 2,
    "movement": 2,
    "resources required": "iron",
    "technology required": "mathematics",
    "type": "CLASSICAL_ERA_UNITS"
  },
  {
    "key" : "horseman",
    "name" : "سوارکار",
    "cost": 70,
    "combat type": "mounted",
    "combat strength": 12,
    "ranged combat strength": "melee",
    "range": "N/A",
    "movement": 4,
    "resources required": "horses",
    "technology required": "horseback riding",
    "type": "CLASSICAL_ERA_UNITS"
  },
  {
    "key" : "swordsman",
    "name" : "شمشیرزن",
    "cost": 70,
    "combat type": "melee",
    "combat strength": 11,
    "ranged combat strength": "N/A",
    "range": "N/A",
    "movement": 2,
    "resources required": "iron",
    "technology required": "iron working",
    "type": "CLASSICAL_ERA_UNITS"
  },
  {
    "key" : "Crossbowman",
    "name" : "کراس کمان",
    "cost": 120,
    "combat type": "archery",
    "combat strength": 6,
    "ranged combat strength": 12,
    "range": 2,
    "movement": 2,
    "resources required": "None",
    "technology required": "machinery",
    "type": "MEDIEVAL_ERA_UNITS"
  },
  {
    "key" : "knight",
    "name" : "شوالیه",
    "cost": 150,
    "combat type": "mounted",
    "combat strength": 18,
    "ranged combat strength": "N/A",
    "range": "N/A",
    "movement": 3,
    "resources required": "horse",
    "technology required": "chivalry",
    "type": "MEDIEVAL_ERA_UNITS"
  },
  {
    "key" : "long sword man",
    "name" : "شمشیر بلند",
    "cost": 150,
    "combat type": "melee",
    "combat strength": 18,
    "ranged combat strength": "N/A",
    "range": "N/A",
    "movement": 3,
    "resources required": "iron",
    "technology required": "steel",
    "type": "MEDIEVAL_ERA_UNITS"
  },
  {
    "key" : "Pikeman",
    "name" : "پایکمن",
    "cost": 100,
    "combat type": "melee",
    "combat strength": 10,
    "ranged combat strength": "N/A",
    "range": "N/A",
    "movement": 2,
    "resources required": "None",
    "technology required": "civil service",
    "type": "MEDIEVAL_ERA_UNITS"
  },
  {
    "key" : "trebuchet",
    "name" : "تربوشت",
    "cost": 170,
    "combat type": "siege",
    "combat strength": 6,
    "ranged combat strength": 20,
    "range": 2,
    "movement": 2,
    "resources required": "iron",
    "technology required": "physics",
    "type": "MEDIEVAL_ERA_UNITS"
  },
  {
    "key" : "canon",
    "name" : "کانون",
    "cost": 250,
    "combat type": "siege",
    "combat strength": 10,
    "ranged combat strength": 26,
    "range": 2,
    "movement": 2,
    "resources required": "None",
    "technology required": "Chemistry",
    "type": "RENAISSANCE_ERA_UNITS"
  },
  {
    "key" : "cavalry",
    "name" : "سواره نظام",
    "cost": 260,
    "combat type": "mounted",
    "combat strength": 25,
    "ranged combat strength": "N/A",
    "range": "N/A",
    "movement": 3,
    "resources required": "horse",
    "technology required": "military science",
    "type": "RENAISSANCE_ERA_UNITS"
  },
  {
    "key" : "lancer",
    "name" : "لنسر",
    "cost": 220,
    "combat type": "mounted",
    "combat strength": 22,
    "ranged combat strength": "N/A",
    "range": "N/A",
    "movement": 4,
    "resources required": "horse",
    "technology required": "metallurgy",
    "type": "RENAISSANCE_ERA_UNITS"
  },
  {
    "key" : "musketman",
    "name" : "تفنگدار یک",
    "cost": 120,
    "combat type": "gunpowder",
    "combat strength": 16,
    "ranged combat strength": "N/A",
    "range": "N/A",
    "movement": 2,
    "resources required": "None",
    "technology required": "gunpowder",
    "type": "RENAISSANCE_ERA_UNITS"
  },
  {
    "key" : "rifleman",
    "name" : "تفنگدار دو",
    "cost": 200,
    "combat type": "gunpowder",
    "combat strength": 25,
    "ranged combat strength": "N/A",
    "range": "N/A",
    "movement": 2,
    "resources required": "None",
    "technology required": "rifling",
    "type": "RENAISSANCE_ERA_UNITS"
  },
  {
    "key" : "anti-tank gun",
    "name" : "اسلحه ضد تانک",
    "cost": 300,
    "combat type": "gunpowder",
    "combat strength": 32,
    "ranged combat strength": "N/A",
    "range": "N/A",
    "movement": 2,
    "resources required": "None",
    "technology required": "replaceable parts",
    "type": "INDUSTRIAL_ERA_UNITS"
  },
  {
    "key" : "artillery",
    "name" : "توپخانه",
    "cost": 420,
    "combat type": "siege",
    "combat strength": 16,
    "ranged combat strength": 32,
    "range": 3,
    "movement": 2,
    "resources required": "None",
    "technology required": "dynamite",
    "type": "INDUSTRIAL_ERA_UNITS"
  },
  {
    "key" : "infantry",
    "name" : "پیاده نظام",
    "cost": 300,
    "combat type": "gunpowder",
    "combat strength": 36,
    "ranged combat strength": "N/A",
    "range": "N/A",
    "movement": 2,
    "resources required": "None",
    "technology required": "replaceable part",
    "type": "INDUSTRIAL_ERA_UNITS"
  },
  {
    "key" : "panzer",
    "name" : "پانزر",
    "cost": 450,
    "combat type": "armored",
    "combat strength": 60,
    "ranged combat strength": null,
    "range": "N/A",
    "movement": 5,
    "resources required": null,
    "technology required": "combustion",
    "type": "INDUSTRIAL_ERA_UNITS"
  },
  {
    "key" : "tank",
    "name" : "تانک",
    "cost": 200,
    "combat type": "gunpowder",
    "combat strength": 50,
    "ranged combat strength": null,
    "range": "N/A",
    "movement": 4,
    "resources required": null,
    "technology required": "combustion",
    "type": "INDUSTRIAL_ERA_UNITS"
  }
]